preprocessy/__init__.py
preprocessy/data_splitting/__init__.py
preprocessy/data_splitting/_kfold.py
preprocessy/data_splitting/_split.py
preprocessy/encoding/__init__.py
preprocessy/encoding/_categorical.py
preprocessy/exceptions.py
preprocessy/feature_selection/__init__.py
preprocessy/feature_selection/_correlation.py
preprocessy/feature_selection/_selectKBest.py
preprocessy/input/__init__.py
preprocessy/input/_read.py
preprocessy/missing_data/__init__.py
preprocessy/missing_data/_main.py
preprocessy/outliers/__init__.py
preprocessy/outliers/_handleoutlier.py
preprocessy/parse/__init__.py
preprocessy/parse/_summarize.py
preprocessy/pipelines/__init__.py
preprocessy/pipelines/_base.py
preprocessy/pipelines/_feature_selection_pipeline.py
preprocessy/pipelines/_standard_pipeline.py
preprocessy/pipelines/config.py
preprocessy/scaling/__init__.py
preprocessy/scaling/_main.py
preprocessy/scaling/math_funcs/scaling_techniques.txt
preprocessy/utils/__init__.py
preprocessy/utils/main.py
preprocessy-1.0.4.dist-info/LICENSE.rst
preprocessy-1.0.4.dist-info/WHEEL
preprocessy-1.0.4.dist-info/METADATA
preprocessy-1.0.4.dist-info/RECORD
