Metadata-Version: 2.1
Name: preprocessy
Version: 1.0.4
Summary: Data Preprocessing framework that provides customizable pipelines.
Home-page: https://preprocessy.readthedocs.io/en/latest/
License: MIT
Keywords: Data Pipelines,Data Preprocessing,Data Science
Author: Saif Kazi
Author-email: saif1204kazi@gmail.com
Requires-Python: >=3.8,<4.0
Classifier: License :: OSI Approved :: MIT License
Classifier: Programming Language :: Python :: 3
Classifier: Programming Language :: Python :: 3.10
Classifier: Programming Language :: Python :: 3.8
Classifier: Programming Language :: Python :: 3.9
Requires-Dist: alive-progress (==2.1.0)
Requires-Dist: colorama (==0.4.4)
Requires-Dist: pandas (==1.3.4)
Requires-Dist: prettytable (==2.1.0)
Requires-Dist: scikit-learn (==0.24.2)
Requires-Dist: stringcase (==1.2.0)
Project-URL: Bug Tracker, https://github.com/preprocessy/preprocessy/issues
Project-URL: Documentation, https://preprocessy.readthedocs.io/en/latest/api/
Project-URL: Repository, https://github.com/preprocessy/preprocessy
